xcompose/__init__.py
xcompose/keysymdef.h
xcompose-0.5.1.dist-info/METADATA
xcompose-0.5.1.dist-info/WHEEL
xcompose-0.5.1.dist-info/entry_points.txt
xcompose-0.5.1.dist-info/licenses/LICENSE
xcompose-0.5.1.dist-info/RECORD
