Metadata-Version: 2.4
Name: xcompose
Version: 0.5.1
Summary: Utility for managing X11 compose key sequences
Project-URL: config, https://github.com/Udzu/xcompose/blob/main/Compose
Author-email: Uri Granta <uri.granta+python@gmail.com>
License: MIT
License-File: LICENSE
Keywords: Compose key,Unicode,text entry,xcompose
Classifier: Development Status :: 4 - Beta
Classifier: Environment :: Console
Classifier: Intended Audience :: End Users/Desktop
Classifier: License :: OSI Approved :: MIT License
Classifier: Operating System :: POSIX :: Linux
Classifier: Programming Language :: Python
Classifier: Topic :: Text Processing
Classifier: Topic :: Utilities
Requires-Python: >=3.10
Requires-Dist: pygtrie>=2.5.0
